langfoundation/callback/__init__.py
langfoundation/callback/base/__init__.py
langfoundation/callback/base/base.py
langfoundation/callback/base/records/__init__.py
langfoundation/callback/base/records/agent.py
langfoundation/callback/base/records/base.py
langfoundation/callback/base/records/retriever.py
langfoundation/callback/base/records/token.py
langfoundation/callback/base/records/tool.py
langfoundation/callback/base/tags.py
langfoundation/callback/debug/log/__init__.py
langfoundation/callback/debug/log/callback.py
langfoundation/callback/debug/log/type.py
langfoundation/callback/debug/stream/__init__.py
langfoundation/callback/debug/stream/callback.py
langfoundation/chain/chain/__init__.py
langfoundation/chain/chain/base.py
langfoundation/chain/graph/__init__.py
langfoundation/chain/graph/graph/__init__.py
langfoundation/chain/graph/graph/base.py
langfoundation/chain/graph/node/__init__.py
langfoundation/chain/graph/node/base.py
langfoundation/chain/graph/node/input.py
langfoundation/chain/graph/node/partial.py
langfoundation/chain/graph/node/template.py
langfoundation/chain/prompt/__init__.py
langfoundation/chain/prompt/template.py
langfoundation/errors/chain.py
langfoundation/errors/max_retry.py
langfoundation/modelhub/__init__.py
langfoundation/modelhub/chat/__init__.py
langfoundation/modelhub/chat/config.py
langfoundation/modelhub/chat/params.py
langfoundation/modelhub/rerank/__init__.py
langfoundation/modelhub/rerank/base.py
langfoundation/parser/__init__.py
langfoundation/parser/agent/__init__.py
langfoundation/parser/agent/model.py
langfoundation/parser/agent/parser.py
langfoundation/parser/display/__init__.py
langfoundation/parser/display/parser.py
langfoundation/parser/pydantic/__init__.py
langfoundation/parser/pydantic/parser.py
langfoundation/parser/pydantic/template.py
langfoundation/py.typed
langfoundation/utils/debug/__init__.py
langfoundation/utils/debug/formatter.py
langfoundation/utils/debug/log/__init__.py
langfoundation-1.6.0.dist-info/METADATA
langfoundation-1.6.0.dist-info/WHEEL
langfoundation-1.6.0.dist-info/RECORD
